did/__init__.py
did/colors.py
did/main.py
did_py-0.0.17.dist-info/LICENSE
did_py-0.0.17.dist-info/METADATA
did_py-0.0.17.dist-info/WHEEL
did_py-0.0.17.dist-info/entry_points.txt
did_py-0.0.17.dist-info/top_level.txt
did_py-0.0.17.dist-info/RECORD
