Metadata-Version: 2.1
Name: did-py
Version: 0.0.17
Summary: what did i do?
Author-email: Casey Williams <caseyjw@mail.com>
License: MIT
Project-URL: github, https://github.com/shnupta/did
Keywords: time-management,tasks,productivity
Requires-Python: >=3.7
License-File: LICENSE
